pyipasnhistory/__init__.py
pyipasnhistory/api.py
pyipasnhistory/py.typed
pyipasnhistory-2.1.5.dist-info/METADATA
pyipasnhistory-2.1.5.dist-info/WHEEL
pyipasnhistory-2.1.5.dist-info/entry_points.txt
pyipasnhistory-2.1.5.dist-info/RECORD
