Metadata-Version: 2.3
Name: pyipasnhistory
Version: 2.1.5
Summary: Python client for IP ASN History
License: AGPL
Author: Raphaël Vinot
Author-email: raphael.vinot@circl.lu
Requires-Python: >=3.9
Classifier: Development Status :: 5 - Production/Stable
Classifier: Environment :: Console
Classifier: Intended Audience :: Information Technology
Classifier: Intended Audience :: Science/Research
Classifier: Intended Audience :: Telecommunications Industry
Classifier: License :: Other/Proprietary License
Classifier: Operating System :: POSIX :: Linux
Classifier: Programming Language :: Python :: 3
Classifier: Programming Language :: Python :: 3.9
Classifier: Programming Language :: Python :: 3.10
Classifier: Programming Language :: Python :: 3.11
Classifier: Programming Language :: Python :: 3.12
Classifier: Programming Language :: Python :: 3.13
Classifier: Topic :: Internet
Classifier: Topic :: Security
Provides-Extra: docs
Requires-Dist: Sphinx (>=8.2.3) ; (python_version >= "3.11") and (extra == "docs")
Requires-Dist: requests (>=2.32.4)
Project-URL: Documentation, https://pyipasnhistory.readthedocs.io/en/latest/
Project-URL: Repository, https://github.com/D4-project/pyipasnhistory
